tekimax/__init__.py
tekimax/_base_client.py
tekimax/_client.py
tekimax/_compat.py
tekimax/_constants.py
tekimax/_exceptions.py
tekimax/_files.py
tekimax/_models.py
tekimax/_qs.py
tekimax/_resource.py
tekimax/_response.py
tekimax/_streaming.py
tekimax/_types.py
tekimax/_version.py
tekimax/py.typed
tekimax/_utils/__init__.py
tekimax/_utils/_compat.py
tekimax/_utils/_datetime_parse.py
tekimax/_utils/_logs.py
tekimax/_utils/_proxy.py
tekimax/_utils/_reflection.py
tekimax/_utils/_resources_proxy.py
tekimax/_utils/_streams.py
tekimax/_utils/_sync.py
tekimax/_utils/_transform.py
tekimax/_utils/_typing.py
tekimax/_utils/_utils.py
tekimax/lib/.keep
tekimax/resources/__init__.py
tekimax/resources/activity_log.py
tekimax/resources/agent.py
tekimax/resources/attribution_report.py
tekimax/resources/contest_outcome.py
tekimax/resources/metrics.py
tekimax/resources/provenance.py
tekimax/resources/redress.py
tekimax/resources/signoff.py
tekimax/resources/stream_learning_content.py
tekimax/resources/transparency.py
tekimax/resources/user.py
tekimax/types/__init__.py
tekimax/types/activity_log_list_params.py
tekimax/types/activity_log_list_response.py
tekimax/types/agent_list_tools_response.py
tekimax/types/agent_orchestrate_params.py
tekimax/types/agent_orchestrate_response.py
tekimax/types/attribution_report_retrieve_params.py
tekimax/types/attribution_report_retrieve_response.py
tekimax/types/contest_outcome_create_params.py
tekimax/types/contest_outcome_create_response.py
tekimax/types/metric_retrieve_dashboard_response.py
tekimax/types/provenance_retrieve_response.py
tekimax/types/redress_trigger_params.py
tekimax/types/redress_trigger_response.py
tekimax/types/signoff_create_params.py
tekimax/types/signoff_create_response.py
tekimax/types/stream_learning_content_create_params.py
tekimax/types/stream_learning_content_create_response.py
tekimax/types/transparency_retrieve_response.py
tekimax/types/user_auto_detect_modality_profile_params.py
tekimax-0.5.0.dist-info/METADATA
tekimax-0.5.0.dist-info/WHEEL
tekimax-0.5.0.dist-info/licenses/LICENSE
tekimax-0.5.0.dist-info/RECORD
